{
  "benchmark": "AppWorld public dev/train stateful slice",
  "method": "rave_appworld_slice",
  "agent": "deterministic",
  "model": "",
  "experiment_name": "appworld_gmail_star_relationship_20260524",
  "task_ids": [
    "0de03ad_1",
    "0de03ad_2",
    "0de03ad_3"
  ],
  "appworld_root": "appworld_020_root",
  "note": "This is a targeted public AppWorld slice, not a full AppWorld leaderboard run. It does not use ground-truth solution code or ground-truth public_data to construct actions."
}